[
  {
    "appId": 810011,
    "name": "Microsoft Office",
    "appType": "curated",
    "packageName": "microsoft-office",
    "iconUrl": "https://raw.githubusercontent.com/simple-icons/simple-icons/develop/icons/microsoftoffice.svg",
    "headerImage": "https://images.unsplash.com/photo-1667372393119-c85c020799a3?w=800&h=450&fit=crop",
    "screenshots": [
      "https://images.unsplash.com/photo-1664575602276-acd073f104c1?w=800&h=500&fit=crop",
      "https://images.unsplash.com/photo-1667372393119-c85c020799a3?w=800&h=500&fit=crop"
    ],
    "shortDescription": "微软办公软件套件，包含 Word、Excel、PowerPoint，是办公事实标准，格式兼容性最佳。",
    "detailedDescription": "Microsoft Office 是全球最广泛使用的办公软件套件，包含 Word（文字处理）、Excel（电子表格）、PowerPoint（演示文稿）、Outlook（电子邮件）等核心组件。它对 DOCX、XLSX、PPTX 等微软专有格式的兼容性最好，支持 VBA 宏、复杂的公式和高级排版。虽然安卓版 Office 存在，但功能明显弱于桌面版，特别是 VBA、插件、复杂文档处理能力缺失。",
    "genres": ["生产力", "办公软件", "文字处理"],
    "isFree": false,
    "price": "付费订阅",
    "developers": "Microsoft",
    "publishers": "Microsoft",
    "releaseDate": "2024-06-01",
    "protonTier": "gold",
    "totalReports": 1245,
    "downloadSize": 314572800,
    "winlatorNotes": "推荐使用 Office 2010/2013/2016，避免 Office 365 订阅验证问题。建议安装 .NET Framework 4.8 和 Visual C++ 运行库。关闭自动保存和实时协作功能可提升稳定性。",
    "downloadUrl": "https://www.microsoft.com/microsoft-365",
    "officialSite": "https://www.microsoft.com/microsoft-365"
  },
  {
    "appId": 810012,
    "name": "Foxit PDF Editor",
    "appType": "curated",
    "packageName": "foxit-pdf-editor",
    "iconUrl": "https://raw.githubusercontent.com/simple-icons/simple-icons/develop/icons/foxit.svg",
    "headerImage": "https://images.unsplash.com/photo-1568992687947-868a62a9f521?w=800&h=450&fit=crop",
    "screenshots": [
      "https://images.unsplash.com/photo-1568992687947-868a62a9f521?w=800&h=500&fit=crop",
      "https://images.unsplash.com/photo-1586281380349-632531db7ed4?w=800&h=500&fit=crop"
    ],
    "shortDescription": "功能全面的 PDF 编辑软件，支持文本编辑、注释、表单填写、OCR、数字签名等专业功能。",
    "detailedDescription": "Foxit PDF Editor 是一款功能强大的 PDF 编辑软件，支持直接编辑 PDF 文本和图像、添加注释和标记、填写和创建表单、OCR 文字识别、数字签名、文档加密等专业功能。它体积小巧、启动速度快，与 Adobe Acrobat 高度兼容。虽然安卓版 Foxit 存在，但编辑、表单、OCR 和批量处理能力远弱于桌面版。",
    "genres": ["生产力", "PDF工具", "文档编辑"],
    "isFree": false,
    "price": "付费",
    "developers": "Foxit Software",
    "publishers": "Foxit Software Inc.",
    "releaseDate": "2024-04-15",
    "protonTier": "gold",
    "totalReports": 156,
    "downloadSize": 83886080,
    "winlatorNotes": "编辑和注释功能稳定。OCR 功能需要额外安装语言包。建议关闭云同步功能以避免兼容性问题。表单填写和数字签名功能可用。",
    "downloadUrl": "https://www.foxit.com/pdf-editor/",
    "officialSite": "https://www.foxit.com"
  },
  {
    "appId": 810013,
    "name": "PDF-XChange Editor",
    "appType": "curated",
    "packageName": "pdf-xchange-editor",
    "iconUrl": "https://raw.githubusercontent.com/simple-icons/simple-icons/develop/icons/pdf.svg",
    "headerImage": "https://images.unsplash.com/photo-1568992687947-868a62a9f521?w=800&h=450&fit=crop",
    "screenshots": [
      "https://images.unsplash.com/photo-1586281380349-632531db7ed4?w=800&h=500&fit=crop",
      "https://images.unsplash.com/photo-1568992687947-868a62a9f521?w=800&h=500&fit=crop"
    ],
    "shortDescription": "轻量快速的 PDF 阅读器和编辑器，注释功能强大，OCR 支持好，体积小巧。",
    "detailedDescription": "PDF-XChange Editor 是 Windows 平台上最快的 PDF 阅读器和编辑器之一，体积小巧但功能强大。它支持 PDF 注释、高亮、划线、便签、图章、表单填写、OCR 文字识别、PDF 转图片/Word 等功能。界面简洁，启动速度极快，是 Foxit 和 Adobe Acrobat 的轻量替代品。",
    "genres": ["生产力", "PDF工具", "文档编辑"],
    "isFree": true,
    "price": "免费版",
    "developers": "Tracker Software Products",
    "publishers": "Tracker Software Products Ltd.",
    "releaseDate": "2024-05-20",
    "protonTier": "gold",
    "totalReports": 134,
    "downloadSize": 52428800,
    "winlatorNotes": "运行流畅，注释功能齐全。免费版有水印，但功能足够日常使用。OCR 功能需要单独安装语言包。建议关闭自动更新。",
    "downloadUrl": "https://www.tracker-software.com/product/pdf-xchange-editor",
    "officialSite": "https://www.tracker-software.com"
  },
  {
    "appId": 810014,
    "name": "Adobe Acrobat Reader DC",
    "appType": "curated",
    "packageName": "adobe-acrobat-reader",
    "iconUrl": "https://raw.githubusercontent.com/simple-icons/simple-icons/develop/icons/adobeacrobatreader.svg",
    "headerImage": "https://images.unsplash.com/photo-1568992687947-868a62a9f521?w=800&h=450&fit=crop",
    "screenshots": [
      "https://images.unsplash.com/photo-1586281380349-632531db7ed4?w=800&h=500&fit=crop",
      "https://images.unsplash.com/photo-1568992687947-868a62a9f521?w=800&h=500&fit=crop"
    ],
    "shortDescription": "Adobe 官方 PDF 阅读器，支持注释、表单填写、数字签名，PDF 标准兼容性最好。",
    "detailedDescription": "Adobe Acrobat Reader DC 是 Adobe 官方推出的免费 PDF 阅读器，支持查看、注释、填写表单、数字签名、PDF 转 Word/Excel 等功能。它拥有最好的 PDF 标准兼容性和渲染准确性，支持 3D PDF、多媒体 PDF、PDF/A 等高级特性。虽然安卓版存在，但功能受限，许多企业级 PDF 功能缺失。",
    "genres": ["生产力", "PDF工具", "文档阅读"],
    "isFree": true,
    "price": "免费版",
    "developers": "Adobe",
    "publishers": "Adobe Inc.",
    "releaseDate": "2024-03-12",
    "protonTier": "silver",
    "totalReports": 203,
    "downloadSize": 104857600,
    "winlatorNotes": "阅读和注释功能稳定。数字签名需要额外配置证书。建议禁用自动更新和云同步以减少问题。部分 3D PDF 功能可能无法正常工作。",
    "downloadUrl": "https://get.adobe.com/reader/",
    "officialSite": "https://acrobat.adobe.com"
  }
]
